src/__init__.py
src/cli.py
src/connection_manager.py
src/connection_utility.py
src/main_call.py
src/output.gv
src/output.png
connectionvault-2.2.1.dist-info/LICENSE
connectionvault-2.2.1.dist-info/METADATA
connectionvault-2.2.1.dist-info/WHEEL
connectionvault-2.2.1.dist-info/entry_points.txt
connectionvault-2.2.1.dist-info/RECORD
