Metadata-Version: 2.3
Name: connectionvault
Version: 2.2.1
Summary: help with connection details
License: MIT
Author: ankit
Author-email: ankit48365@gmail.com
Requires-Python: >=3.11,<4.0
Classifier: License :: OSI Approved :: MIT License
Classifier: Programming Language :: Python :: 3
Classifier: Programming Language :: Python :: 3.11
Classifier: Programming Language :: Python :: 3.12
Classifier: Programming Language :: Python :: 3.13
Requires-Dist: PyYAML (>=6.0.2,<7.0.0)
Requires-Dist: SQLAlchemy (>=2.0.36,<3.0.0)
Requires-Dist: mysql-connector-python (>=9.3.0,<10.0.0)
Requires-Dist: pandas (>=2.2.3,<3.0.0)
Requires-Dist: poetry (>=1.8.4,<2.0.0)
Requires-Dist: psycopg2 (>=2.9.10,<3.0.0)
Requires-Dist: pylint (>=3.3.1,<4.0.0)
Requires-Dist: pyodbc (>=5.2.0,<6.0.0)
Requires-Dist: tabulate (>=0.9.0,<0.10.0)
